{
  "items": [
    {
      "track": {
        "name": "New Game"
      }
    },
    {
      "track": {
        "name": "Apollo (Barely Alive Remix)"
      }
    },
    {
      "track": {
        "name": "Pinball"
      }
    },
    {
      "track": {
        "name": "Rain (Stephen Walking Remix)"
      }
    },
    {
      "track": {
        "name": "Decisions"
      }
    },
    {
      "track": {
        "name": "Fugitive"
      }
    },
    {
      "track": {
        "name": "Error Code"
      }
    },
    {
      "track": {
        "name": "Savage"
      }
    },
    {
      "track": {
        "name": "Beam Me Up (Kill Mode) (Radio Edit)"
      }
    },
    {
      "track": {
        "name": "Acid Wolfpack - Original Mix"
      }
    },
    {
      "track": {
        "name": "Derezzed - Remixed by The Glitch Mob"
      }
    },
    {
      "track": {
        "name": "The Veldt - Tommy Trash Remix"
      }
    },
    {
      "track": {
        "name": "I.D.G.A.F.O.S."
      }
    },
    {
      "track": {
        "name": "Flying Spaghetti Monster"
      }
    },
    {
      "track": {
        "name": "Tetris"
      }
    },
    {
      "track": {
        "name": "Keep on Rocking"
      }
    },
    {
      "track": {
        "name": "Far From Home - Farleon Remix"
      }
    },
    {
      "track": {
        "name": "Blood Red - Original Mix"
      }
    },
    {
      "track": {
        "name": "One Click Headshot - Original Mix"
      }
    },
    {
      "track": {
        "name": "Do Or Die (feat. Childish Gambino)"
      }
    },
    {
      "track": {
        "name": "Hello?"
      }
    },
    {
      "track": {
        "name": "Full Grizzly"
      }
    },
    {
      "track": {
        "name": "Reach"
      }
    },
    {
      "track": {
        "name": "I Don’t Wanna Die - Borgore Remix"
      }
    },
    {
      "track": {
        "name": "Where Did I Go? - Dillon Francis & Kill Paris Remix"
      }
    },
    {
      "track": {
        "name": "Jurassic"
      }
    },
    {
      "track": {
        "name": "Bad Pitched"
      }
    },
    {
      "track": {
        "name": "Genesis"
      }
    },
    {
      "track": {
        "name": "Green Hill - Original Mix"
      }
    },
    {
      "track": {
        "name": "Rage Valley"
      }
    },
    {
      "track": {
        "name": "Manslaughter (VIP Mix)"
      }
    },
    {
      "track": {
        "name": "Finale"
      }
    },
    {
      "track": {
        "name": "Shuriken"
      }
    },
    {
      "track": {
        "name": "Give My Regards - Original Mix"
      }
    },
    {
      "track": {
        "name": "Entropy"
      }
    },
    {
      "track": {
        "name": "Best of 2014 (Album Mix - Part 1)"
      }
    },
    {
      "track": {
        "name": "Best of 2014 (Album Mix - Part 2)"
      }
    },
    {
      "track": {
        "name": "Rave Through the Apocalypse"
      }
    },
    {
      "track": {
        "name": "Rainbow Road"
      }
    },
    {
      "track": {
        "name": "Breakdown VIP"
      }
    },
    {
      "track": {
        "name": "Another World"
      }
    },
    {
      "track": {
        "name": "Bassline Kickin"
      }
    },
    {
      "track": {
        "name": "Emergency"
      }
    },
    {
      "track": {
        "name": "Gunpoint (Edit)"
      }
    },
    {
      "track": {
        "name": "Here It Comes"
      }
    },
    {
      "track": {
        "name": "Hero (feat. Elizaveta)"
      }
    },
    {
      "track": {
        "name": "High Roller - Krafty Kuts Remix"
      }
    },
    {
      "track": {
        "name": "20K"
      }
    },
    {
      "track": {
        "name": "Self Destruct"
      }
    },
    {
      "track": {
        "name": "Disconnected"
      }
    },
    {
      "track": {
        "name": "Razor Sharp"
      }
    },
    {
      "track": {
        "name": "Galactic Voyage"
      }
    },
    {
      "track": {
        "name": "Spitfire"
      }
    },
    {
      "track": {
        "name": "Wut!"
      }
    },
    {
      "track": {
        "name": "Scorpion Pit"
      }
    },
    {
      "track": {
        "name": "Sledgehammer - Original Mix"
      }
    },
    {
      "track": {
        "name": "Kali 47 - Original Mix"
      }
    },
    {
      "track": {
        "name": "Prelude - Original Mix"
      }
    },
    {
      "track": {
        "name": "Nightmare Adventures - Original Mix"
      }
    },
    {
      "track": {
        "name": "Starfish - Original Mix"
      }
    },
    {
      "track": {
        "name": "Ism - Original Mix"
      }
    },
    {
      "track": {
        "name": "Without A Name - Original Mix"
      }
    },
    {
      "track": {
        "name": "Reptile's Theme"
      }
    },
    {
      "track": {
        "name": "Scatta - feat. Foreign Beggars & Bare Noize"
      }
    },
    {
      "track": {
        "name": "Top of the World 2"
      }
    },
    {
      "track": {
        "name": "Excellent Choice"
      }
    },
    {
      "track": {
        "name": "Boombox"
      }
    },
    {
      "track": {
        "name": "Next Big Thing"
      }
    },
    {
      "track": {
        "name": "Who We Are"
      }
    },
    {
      "track": {
        "name": "Too Simple"
      }
    },
    {
      "track": {
        "name": "Dance to It"
      }
    },
    {
      "track": {
        "name": "Dragon Pirates"
      }
    },
    {
      "track": {
        "name": "Drink Up"
      }
    },
    {
      "track": {
        "name": "Hot Pursuit"
      }
    },
    {
      "track": {
        "name": "Universal"
      }
    },
    {
      "track": {
        "name": "Cloak and Dagger"
      }
    },
    {
      "track": {
        "name": "The Legend Of Zelda - Original Mix"
      }
    },
    {
      "track": {
        "name": "Nuclear (Hands Up)"
      }
    },
    {
      "track": {
        "name": "Permutate"
      }
    },
    {
      "track": {
        "name": "The Follower"
      }
    },
    {
      "track": {
        "name": "The Passing"
      }
    },
    {
      "track": {
        "name": "Free"
      }
    },
    {
      "track": {
        "name": "Sidewinder"
      }
    },
    {
      "track": {
        "name": "Delayed Friend Request"
      }
    },
    {
      "track": {
        "name": "Peacock"
      }
    },
    {
      "track": {
        "name": "Retro City"
      }
    },
    {
      "track": {
        "name": "Close Encounter"
      }
    },
    {
      "track": {
        "name": "Dreaming"
      }
    },
    {
      "track": {
        "name": "Power Glove"
      }
    },
    {
      "track": {
        "name": "Goro's Theme"
      }
    },
    {
      "track": {
        "name": "The Divide"
      }
    },
    {
      "track": {
        "name": "Till It's Over"
      }
    },
    {
      "track": {
        "name": "To the Stars"
      }
    },
    {
      "track": {
        "name": "Organ Donor - Original Mix"
      }
    },
    {
      "track": {
        "name": "Clockwork"
      }
    },
    {
      "track": {
        "name": "Cloud Nine"
      }
    },
    {
      "track": {
        "name": "Surface"
      }
    },
    {
      "track": {
        "name": "Act III"
      }
    },
    {
      "track": {
        "name": "Pinball (Twine Remix)"
      }
    },
    {
      "track": {
        "name": "Killin' It"
      }
    },
    {
      "track": {
        "name": "Alphabet Aerobics"
      }
    },
    {
      "track": {
        "name": "Out on a Limb (feat. Jonny Rose)"
      }
    },
    {
      "track": {
        "name": "Dream of You"
      }
    },
    {
      "track": {
        "name": "FTW"
      }
    },
    {
      "track": {
        "name": "Bohemian Rhapsody"
      }
    },
    {
      "track": {
        "name": "Pressure - Original Mix"
      }
    },
    {
      "track": {
        "name": "Sweet"
      }
    },
    {
      "track": {
        "name": "Night Rider (feat. Phoebe Ray)"
      }
    },
    {
      "track": {
        "name": "Try This"
      }
    },
    {
      "track": {
        "name": "Boundaries"
      }
    },
    {
      "track": {
        "name": "Prism"
      }
    },
    {
      "track": {
        "name": "Ambush"
      }
    },
    {
      "track": {
        "name": "Welcome to Planet Urf"
      }
    },
    {
      "track": {
        "name": "Kinetic (The Crystal Method vs. Dada Life)"
      }
    },
    {
      "track": {
        "name": "Concussive (Bassnectar vs. Renholdër)"
      }
    },
    {
      "track": {
        "name": "Once Again"
      }
    },
    {
      "track": {
        "name": "Quantum"
      }
    },
    {
      "track": {
        "name": "Battle Cry"
      }
    },
    {
      "track": {
        "name": "Cheat Codes"
      }
    },
    {
      "track": {
        "name": "Shark City"
      }
    },
    {
      "track": {
        "name": "Growing Up (feat. Openwater)"
      }
    },
    {
      "track": {
        "name": "50K - Original Mix"
      }
    },
    {
      "track": {
        "name": "Future Proof (Original Mix)"
      }
    },
    {
      "track": {
        "name": "R U Ready (Original Mix)"
      }
    },
    {
      "track": {
        "name": "Chop Suey!"
      }
    },
    {
      "track": {
        "name": "B.Y.O.B."
      }
    },
    {
      "track": {
        "name": "Lonely Day"
      }
    },
    {
      "track": {
        "name": "Toxicity"
      }
    },
    {
      "track": {
        "name": "Aerials"
      }
    },
    {
      "track": {
        "name": "Hypnotize"
      }
    },
    {
      "track": {
        "name": "Revenga"
      }
    },
    {
      "track": {
        "name": "War?"
      }
    },
    {
      "track": {
        "name": "Insight"
      }
    },
    {
      "track": {
        "name": "Party Gwarn"
      }
    },
    {
      "track": {
        "name": "Pistons"
      }
    },
    {
      "track": {
        "name": "Crave You - Adventure Club Remix"
      }
    },
    {
      "track": {
        "name": "Kick Out The Epic Motherf**ker - Vocal Version"
      }
    },
    {
      "track": {
        "name": "Pitiless - Costello Remix"
      }
    },
    {
      "track": {
        "name": "I Don't Like You - Nicky Romero Remix"
      }
    },
    {
      "track": {
        "name": "Brainfreeze - Original Mix"
      }
    },
    {
      "track": {
        "name": "BONK! - Original Mix"
      }
    },
    {
      "track": {
        "name": "Damage Control - Original Mix"
      }
    },
    {
      "track": {
        "name": "Breakfast of Champions - Original Mix"
      }
    },
    {
      "track": {
        "name": "Better Wipe That Up - Original Mix"
      }
    },
    {
      "track": {
        "name": "You Missed A Spot - Original Mix"
      }
    },
    {
      "track": {
        "name": "Latch"
      }
    },
    {
      "track": {
        "name": "Sandstorm - Original Mix"
      }
    },
    {
      "track": {
        "name": "One Week"
      }
    },
    {
      "track": {
        "name": "Five Hours"
      }
    },
    {
      "track": {
        "name": "Bring the Madness (feat. Mayor Apeshit)"
      }
    },
    {
      "track": {
        "name": "Popcorn Funk - Original Mix"
      }
    },
    {
      "track": {
        "name": "Send Me Your Love - KDrew Remix"
      }
    },
    {
      "track": {
        "name": "Juicy Wiggle"
      }
    },
    {
      "track": {
        "name": "Adventures"
      }
    },
    {
      "track": {
        "name": "Get Jinxed"
      }
    },
    {
      "track": {
        "name": "Canvas"
      }
    },
    {
      "track": {
        "name": "Waves - Robin Schulz Radio Edit"
      }
    },
    {
      "track": {
        "name": "Let Me Hit It - Audiostalkers Original Mix"
      }
    },
    {
      "track": {
        "name": "Bass Head"
      }
    },
    {
      "track": {
        "name": "Heads Up"
      }
    },
    {
      "track": {
        "name": "Whatta Mask"
      }
    },
    {
      "track": {
        "name": "We Are Back - The S Remix"
      }
    },
    {
      "track": {
        "name": "Vancouver Beatdown - Original Mix"
      }
    },
    {
      "track": {
        "name": "Hoedown - Original Mix"
      }
    },
    {
      "track": {
        "name": "City 2 City Ft. Belle Humble - Original Mix"
      }
    },
    {
      "track": {
        "name": "Nevermind"
      }
    },
    {
      "track": {
        "name": "Nothing to Say"
      }
    },
    {
      "track": {
        "name": "U R So Fucked"
      }
    },
    {
      "track": {
        "name": "The Rat"
      }
    },
    {
      "track": {
        "name": "Nation of Wusses"
      }
    },
    {
      "track": {
        "name": "Wanted To"
      }
    },
    {
      "track": {
        "name": "Serve My Thirst"
      }
    },
    {
      "track": {
        "name": "Drum n Baasa"
      }
    },
    {
      "track": {
        "name": "The Pretender"
      }
    },
    {
      "track": {
        "name": "The Messenger 2012"
      }
    },
    {
      "track": {
        "name": "Down The Road"
      }
    },
    {
      "track": {
        "name": "The Cell"
      }
    },
    {
      "track": {
        "name": "Take Me Home (feat. Bebe Rexha)"
      }
    },
    {
      "track": {
        "name": "Overtime"
      }
    },
    {
      "track": {
        "name": "Kiss the Sky"
      }
    },
    {
      "track": {
        "name": "Here and Now (feat. Kerli)"
      }
    },
    {
      "track": {
        "name": "Satellites"
      }
    },
    {
      "track": {
        "name": "Hideaway"
      }
    },
    {
      "track": {
        "name": "Swingish - Bonus Track"
      }
    },
    {
      "track": {
        "name": "Stretched"
      }
    },
    {
      "track": {
        "name": "State of Ghetto Jackin' (feat. DJ Nasty)"
      }
    },
    {
      "track": {
        "name": "Sleaze - feat. Mistajam"
      }
    },
    {
      "track": {
        "name": "Scream - Original Mix"
      }
    },
    {
      "track": {
        "name": "Rocket"
      }
    },
    {
      "track": {
        "name": "Punish The Wanker - Original Mix"
      }
    },
    {
      "track": {
        "name": "Predator - Cyberoptix Remix"
      }
    },
    {
      "track": {
        "name": "Paradox - Original Mix"
      }
    },
    {
      "track": {
        "name": "Minibar"
      }
    },
    {
      "track": {
        "name": "Leperchaun"
      }
    },
    {
      "track": {
        "name": "Kill EVERYBODY"
      }
    },
    {
      "track": {
        "name": "Jump And Shout - Lazy Rich Remix"
      }
    },
    {
      "track": {
        "name": "Iron - Mystery Jets Remix"
      }
    },
    {
      "track": {
        "name": "Ice Jump - Original Mix"
      }
    },
    {
      "track": {
        "name": "I Like Trains (Remix)"
      }
    },
    {
      "track": {
        "name": "Horus The Chorus"
      }
    },
    {
      "track": {
        "name": "Here We Go - Original Mix"
      }
    },
    {
      "track": {
        "name": "Grand Theft Ecstasy - Original Mix"
      }
    },
    {
      "track": {
        "name": "Falling - Tommy Trash Version"
      }
    },
    {
      "track": {
        "name": "EDM Death Machine"
      }
    },
    {
      "track": {
        "name": "DUBSTEP GUNS (Bonus Track)"
      }
    },
    {
      "track": {
        "name": "Do I See Color"
      }
    },
    {
      "track": {
        "name": "Deadweight - Original Mix"
      }
    },
    {
      "track": {
        "name": "Civilization"
      }
    },
    {
      "track": {
        "name": "Catch You"
      }
    },
    {
      "track": {
        "name": "Beast"
      }
    },
    {
      "track": {
        "name": "Baggy Bottom Boys"
      }
    },
    {
      "track": {
        "name": "Back Again"
      }
    },
    {
      "track": {
        "name": "Bad Selection"
      }
    },
    {
      "track": {
        "name": "Sofi Needs a Ladder"
      }
    },
    {
      "track": {
        "name": "Digital World"
      }
    },
    {
      "track": {
        "name": "Anthem"
      }
    },
    {
      "track": {
        "name": "Ball Point"
      }
    },
    {
      "track": {
        "name": "Chodge Darger"
      }
    },
    {
      "track": {
        "name": "8 Bit Adventure"
      }
    },
    {
      "track": {
        "name": "Night Shade"
      }
    },
    {
      "track": {
        "name": "Funky Sundays"
      }
    },
    {
      "track": {
        "name": "Lightbringer (feat. Pentakill)"
      }
    },
    {
      "track": {
        "name": "Deathfire Grasp (feat. Pentakill)"
      }
    },
    {
      "track": {
        "name": "Cinema - Radio Edit"
      }
    },
    {
      "track": {
        "name": "Atlantic"
      }
    },
    {
      "track": {
        "name": "I'm an Albatraoz"
      }
    },
    {
      "track": {
        "name": "Shine A Light - Flight Facilities Remix"
      }
    },
    {
      "track": {
        "name": "Run"
      }
    },
    {
      "track": {
        "name": "The Sweet Escape"
      }
    },
    {
      "track": {
        "name": "All In - Original Mix"
      }
    },
    {
      "track": {
        "name": "Patience"
      }
    },
    {
      "track": {
        "name": "Carousel"
      }
    },
    {
      "track": {
        "name": "Lessons In Love"
      }
    },
    {
      "track": {
        "name": "Polygon Dust"
      }
    },
    {
      "track": {
        "name": "Duck Hunt"
      }
    },
    {
      "track": {
        "name": "Trndsttr (Lucian Remix) [feat. M. Maggie]"
      }
    },
    {
      "track": {
        "name": "Weapon of Choice 2010 - Lazy Rich Remix"
      }
    },
    {
      "track": {
        "name": "The Alphabeat"
      }
    },
    {
      "track": {
        "name": "Peanut Butter Jelly"
      }
    },
    {
      "track": {
        "name": "Professional Griefers - Vocal Mix"
      }
    },
    {
      "track": {
        "name": "Seeya"
      }
    },
    {
      "track": {
        "name": "One Man Moon Band"
      }
    },
    {
      "track": {
        "name": "Anime Bae"
      }
    },
    {
      "track": {
        "name": "Lean On (feat. MØ & DJ Snake)"
      }
    },
    {
      "track": {
        "name": "Stay High - Habits Remix"
      }
    },
    {
      "track": {
        "name": "Knight"
      }
    },
    {
      "track": {
        "name": "Finish the Fight"
      }
    },
    {
      "track": {
        "name": "One Final Effort"
      }
    },
    {
      "track": {
        "name": "Final Boss"
      }
    },
    {
      "track": {
        "name": "Space Jam"
      }
    },
    {
      "track": {
        "name": "Feelings (Lets Be Friends Remix)"
      }
    },
    {
      "track": {
        "name": "Illusion"
      }
    },
    {
      "track": {
        "name": "Boss Wave"
      }
    },
    {
      "track": {
        "name": "SaharA"
      }
    },
    {
      "track": {
        "name": "This Is How You Know - Original Mix"
      }
    },
    {
      "track": {
        "name": "After Dark"
      }
    },
    {
      "track": {
        "name": "Real Love (feat. Danyka Nadeau)"
      }
    },
    {
      "track": {
        "name": "Flight"
      }
    },
    {
      "track": {
        "name": "Glorious Morning"
      }
    },
    {
      "track": {
        "name": "Aerials"
      }
    },
    {
      "track": {
        "name": "PewDiePie Song - Original Mix"
      }
    },
    {
      "track": {
        "name": "A Race Against Time"
      }
    },
    {
      "track": {
        "name": "Imperium"
      }
    },
    {
      "track": {
        "name": "Cheat Codes"
      }
    },
    {
      "track": {
        "name": "Knight"
      }
    },
    {
      "track": {
        "name": "Crabbuckit"
      }
    },
    {
      "track": {
        "name": "Quantum"
      }
    },
    {
      "track": {
        "name": "Sorry For Party Rocking"
      }
    },
    {
      "track": {
        "name": "Mr. Croissant Taker"
      }
    },
    {
      "track": {
        "name": "Pitiless - Original Mix"
      }
    },
    {
      "track": {
        "name": "Throne"
      }
    },
    {
      "track": {
        "name": "Ready"
      }
    },
    {
      "track": {
        "name": "Here It Comes (Snavs & Toby Green Remix)"
      }
    },
    {
      "track": {
        "name": "Game Changer"
      }
    },
    {
      "track": {
        "name": "Pinball (Dubsidia Remix)"
      }
    },
    {
      "track": {
        "name": "Moonlight (feat. Aloma Steele)"
      }
    },
    {
      "track": {
        "name": "Speeches"
      }
    },
    {
      "track": {
        "name": "Fragile"
      }
    },
    {
      "track": {
        "name": "Edge of the World"
      }
    },
    {
      "track": {
        "name": "Immunity - Original Mix"
      }
    },
    {
      "track": {
        "name": "Cowboy"
      }
    },
    {
      "track": {
        "name": "Be Free"
      }
    },
    {
      "track": {
        "name": "Hurricane"
      }
    },
    {
      "track": {
        "name": "Who We Are"
      }
    },
    {
      "track": {
        "name": "Lady Killa"
      }
    },
    {
      "track": {
        "name": "Raining Blood"
      }
    },
    {
      "track": {
        "name": "Alive feat. Lara Woolf - Original Mix"
      }
    },
    {
      "track": {
        "name": "Waiting for You (feat. Joanna Jones)"
      }
    },
    {
      "track": {
        "name": "Checkpoint"
      }
    },
    {
      "track": {
        "name": "This Will Be the Day (James Landino's Magical Girl Remix)"
      }
    },
    {
      "track": {
        "name": "Time to Say Goodbye (James Landino's Beach Bae Remix)"
      }
    },
    {
      "track": {
        "name": "Party"
      }
    },
    {
      "track": {
        "name": "Break Them (feat. Anna Yvette)"
      }
    },
    {
      "track": {
        "name": "Dynamite"
      }
    },
    {
      "track": {
        "name": "Catfight"
      }
    },
    {
      "track": {
        "name": "Die"
      }
    },
    {
      "track": {
        "name": "By Design"
      }
    },
    {
      "track": {
        "name": "Manslaughter (VIP Mix)"
      }
    },
    {
      "track": {
        "name": "Thrift Shop (feat. Wanz)"
      }
    },
    {
      "track": {
        "name": "Okay"
      }
    },
    {
      "track": {
        "name": "The Beast"
      }
    },
    {
      "track": {
        "name": "Worldwide Choppers"
      }
    },
    {
      "track": {
        "name": "I Know the Truth"
      }
    },
    {
      "track": {
        "name": "Pocket Monsters"
      }
    },
    {
      "track": {
        "name": "Doomsday"
      }
    },
    {
      "track": {
        "name": "Razor Sharp"
      }
    },
    {
      "track": {
        "name": "Pay No Mind"
      }
    },
    {
      "track": {
        "name": "Don't Stop the Party"
      }
    },
    {
      "track": {
        "name": "Damn Daniel - Radio Mix"
      }
    },
    {
      "track": {
        "name": "Cage the Rage"
      }
    },
    {
      "track": {
        "name": "Ocean Man"
      }
    },
    {
      "track": {
        "name": "Get Up! - feat. Skrillex"
      }
    },
    {
      "track": {
        "name": "Day 'N' Nite (nightmare)"
      }
    },
    {
      "track": {
        "name": "Warriors"
      }
    },
    {
      "track": {
        "name": "I Need Your Love"
      }
    },
    {
      "track": {
        "name": "Moar Ghosts 'n' Stuff"
      }
    },
    {
      "track": {
        "name": "Undertale (dj-Jo Remix)"
      }
    },
    {
      "track": {
        "name": "Melodymania"
      }
    },
    {
      "track": {
        "name": "All Alone"
      }
    },
    {
      "track": {
        "name": "Superstar (feat. Krewella)"
      }
    },
    {
      "track": {
        "name": "Go Berzerk"
      }
    },
    {
      "track": {
        "name": "BAMF"
      }
    },
    {
      "track": {
        "name": "Snowblind (feat. Tasha Baxter)"
      }
    },
    {
      "track": {
        "name": "Hunter The Hungry Is Gon’ Eat"
      }
    },
    {
      "track": {
        "name": "Hypnotic - Vanic Remix"
      }
    },
    {
      "track": {
        "name": "Miles Away"
      }
    },
    {
      "track": {
        "name": "Blackout"
      }
    },
    {
      "track": {
        "name": "Shooting Stars"
      }
    },
    {
      "track": {
        "name": "8-Bit Lightsaber - Original Mix"
      }
    },
    {
      "track": {
        "name": "The Beat - Original Mix"
      }
    },
    {
      "track": {
        "name": "Syko - Original Mix"
      }
    },
    {
      "track": {
        "name": "Everything Black (feat. Mike Taylor)"
      }
    },
    {
      "track": {
        "name": "Somewhere to Run"
      }
    },
    {
      "track": {
        "name": "Virtuality"
      }
    },
    {
      "track": {
        "name": "Here With You Now"
      }
    },
    {
      "track": {
        "name": "Against the Sun"
      }
    },
    {
      "track": {
        "name": "Watch Out (feat. Ragga Twins)"
      }
    },
    {
      "track": {
        "name": "Want You"
      }
    },
    {
      "track": {
        "name": "Crazy"
      }
    },
    {
      "track": {
        "name": "Fight"
      }
    },
    {
      "track": {
        "name": "Titans"
      }
    },
    {
      "track": {
        "name": "Believe"
      }
    },
    {
      "track": {
        "name": "I Remember"
      }
    },
    {
      "track": {
        "name": "Possession"
      }
    },
    {
      "track": {
        "name": "Easy Go"
      }
    },
    {
      "track": {
        "name": "Stay (with Alessia Cara)"
      }
    },
    {
      "track": {
        "name": "Jungle"
      }
    },
    {
      "track": {
        "name": "One for All, All for One"
      }
    },
    {
      "track": {
        "name": "Let Go - Original Mix"
      }
    },
    {
      "track": {
        "name": "Facepalm"
      }
    },
    {
      "track": {
        "name": "Disorder"
      }
    },
    {
      "track": {
        "name": "It Ain't Me (with Selena Gomez)"
      }
    },
    {
      "track": {
        "name": "Rottytops Theme (Remix)"
      }
    },
    {
      "track": {
        "name": "Deja Vu (Initial D)"
      }
    },
    {
      "track": {
        "name": "Lone Digger"
      }
    },
    {
      "track": {
        "name": "Clash"
      }
    },
    {
      "track": {
        "name": "Midnight"
      }
    },
    {
      "track": {
        "name": "Ohmwrecker"
      }
    },
    {
      "track": {
        "name": "The Boy Who Shattered Time (feat. Mitis)"
      }
    },
    {
      "track": {
        "name": "Piercing Light (feat. Mako)"
      }
    },
    {
      "track": {
        "name": "Edge of Infinity (feat. Minnesota)"
      }
    },
    {
      "track": {
        "name": "Flash Funk (feat. Marshmello)"
      }
    },
    {
      "track": {
        "name": "Silver Scrapes (As Featured In League of Legends Season 2 World Championship)"
      }
    },
    {
      "track": {
        "name": "Sail - Unlimited Gravity Remix"
      }
    },
    {
      "track": {
        "name": "Freefall - xKore Remix"
      }
    },
    {
      "track": {
        "name": "I’m So Humble"
      }
    },
    {
      "track": {
        "name": "Heavy Metal"
      }
    },
    {
      "track": {
        "name": "Hentai"
      }
    },
    {
      "track": {
        "name": "Believer"
      }
    },
    {
      "track": {
        "name": "Find Me"
      }
    },
    {
      "track": {
        "name": "Let 'em Know (feat. Armanni Reign)"
      }
    },
    {
      "track": {
        "name": "Under Stars"
      }
    },
    {
      "track": {
        "name": "Midnight Hearts - Extended Mix"
      }
    },
    {
      "track": {
        "name": "Beam of Light"
      }
    },
    {
      "track": {
        "name": "THE DROP"
      }
    },
    {
      "track": {
        "name": "Bullseye"
      }
    },
    {
      "track": {
        "name": "Atrium"
      }
    },
    {
      "track": {
        "name": "Bass Jam"
      }
    },
    {
      "track": {
        "name": "Would You Ever"
      }
    },
    {
      "track": {
        "name": "Swamp Thing"
      }
    },
    {
      "track": {
        "name": "Cheat Codes VIP"
      }
    },
    {
      "track": {
        "name": "Warriors of the Night"
      }
    },
    {
      "track": {
        "name": "Bananonymous - Original Mix"
      }
    },
    {
      "track": {
        "name": "Black Magic - Original Mix"
      }
    },
    {
      "track": {
        "name": "Splinter - Original Mix"
      }
    },
    {
      "track": {
        "name": "Pizza Power Alien - Original Mix"
      }
    },
    {
      "track": {
        "name": "Basement - Original Mix"
      }
    },
    {
      "track": {
        "name": "Vario - Original Mix"
      }
    },
    {
      "track": {
        "name": "Turbo Penguin"
      }
    },
    {
      "track": {
        "name": "Smash!"
      }
    }
  ]
}